jobsworthy/__init__.py
jobsworthy/model/__init__.py
jobsworthy/model/model_errors.py
jobsworthy/model/streamer.py
jobsworthy/model/value.py
jobsworthy/observer/__init__.py
jobsworthy/observer/domain/__init__.py
jobsworthy/observer/domain/error.py
jobsworthy/observer/domain/metrics.py
jobsworthy/observer/domain/schema.py
jobsworthy/observer/domain/table.py
jobsworthy/observer/domain/vocab.py
jobsworthy/observer/observer.py
jobsworthy/observer/repo/__init__.py
jobsworthy/observer/repo/observer.py
jobsworthy/performance/__init__.py
jobsworthy/performance/perf_log.py
jobsworthy/performance/repo/performance.py
jobsworthy/repo/__init__.py
jobsworthy/repo/cosmos_repo.py
jobsworthy/repo/hive_repo.py
jobsworthy/repo/properties.py
jobsworthy/repo/readers.py
jobsworthy/repo/repo_messages.py
jobsworthy/repo/spark_db.py
jobsworthy/repo/spark_repo.py
jobsworthy/repo/spark_util.py
jobsworthy/repo/sql_builder.py
jobsworthy/repo/writers.py
jobsworthy/spark_job/__init__.py
jobsworthy/spark_job/command/simple_streamer.py
jobsworthy/spark_job/config.py
jobsworthy/spark_job/spark_job.py
jobsworthy/structure/__init__.py
jobsworthy/structure/puml/__init__.py
jobsworthy/structure/puml/builder/class_model_builder.py
jobsworthy/structure/puml/builder/print_schema_to_puml.py
jobsworthy/structure/puml/cli.py
jobsworthy/structure/puml/code_generator/hive_table_schema.py
jobsworthy/structure/puml/code_generator/puml_generator.py
jobsworthy/structure/puml/code_generator/repo_definition.py
jobsworthy/structure/puml/model/class_model.py
jobsworthy/structure/puml/model_maker.py
jobsworthy/structure/puml/puml_maker.py
jobsworthy/structure/puml/util/error.py
jobsworthy/structure/puml/util/text.py
jobsworthy/structure/puml/writer/file_writer.py
jobsworthy/structure/schema_util.py
jobsworthy/structure/structure.py
jobsworthy/structure/value.py
jobsworthy/structure/vocab_util.py
jobsworthy/util/console.py
jobsworthy/util/databricks.py
jobsworthy/util/dataklass.py
jobsworthy/util/env.py
jobsworthy-0.7.9.dist-info/METADATA
jobsworthy-0.7.9.dist-info/WHEEL
jobsworthy-0.7.9.dist-info/entry_points.txt
jobsworthy-0.7.9.dist-info/RECORD
