Metadata-Version: 2.1
Name: jobsworthy
Version: 0.7.9
Summary: 
Home-page: https://github.com/wildfauve/jobsworth
Author: Col Perks
Author-email: wild.fauve@gmail.com
Requires-Python: >=3.9,<4.0
Classifier: Programming Language :: Python :: 3
Classifier: Programming Language :: Python :: 3.9
Classifier: Programming Language :: Python :: 3.10
Classifier: Programming Language :: Python :: 3.11
Requires-Dist: PyMonad (>=2.4.0,<3.0.0)
Requires-Dist: azure-identity (>=1.11.0,<2.0.0)
Requires-Dist: azure-storage-file-datalake (>=12.9.1,<13.0.0)
Requires-Dist: delta-spark (>=2.1.1,<3.0.0)
Requires-Dist: dependency-injector (>=4.40.0,<5.0.0)
Requires-Dist: pino (>=0.6.0,<0.7.0)
Requires-Dist: pyspark (>=3.3.0,<4.0.0)
Requires-Dist: rdflib (>=6.2.0,<7.0.0)
Requires-Dist: validators (>=0.20.0,<0.21.0)
Project-URL: Repository, https://github.com/wildfauve/jobsworth
